odoo/addons/l10n_it_fatturapa_out/README.rst
odoo/addons/l10n_it_fatturapa_out/__init__.py
odoo/addons/l10n_it_fatturapa_out/__manifest__.py
odoo/addons/l10n_it_fatturapa_out/data/l10n_it_fatturapa_out_data.xml
odoo/addons/l10n_it_fatturapa_out/i18n/am.po
odoo/addons/l10n_it_fatturapa_out/i18n/ar.po
odoo/addons/l10n_it_fatturapa_out/i18n/bg.po
odoo/addons/l10n_it_fatturapa_out/i18n/bs.po
odoo/addons/l10n_it_fatturapa_out/i18n/ca.po
odoo/addons/l10n_it_fatturapa_out/i18n/ca_ES.po
odoo/addons/l10n_it_fatturapa_out/i18n/cs.po
odoo/addons/l10n_it_fatturapa_out/i18n/da.po
odoo/addons/l10n_it_fatturapa_out/i18n/de.po
odoo/addons/l10n_it_fatturapa_out/i18n/el_GR.po
odoo/addons/l10n_it_fatturapa_out/i18n/en_AU.po
odoo/addons/l10n_it_fatturapa_out/i18n/en_GB.po
odoo/addons/l10n_it_fatturapa_out/i18n/es.po
odoo/addons/l10n_it_fatturapa_out/i18n/es_AR.po
odoo/addons/l10n_it_fatturapa_out/i18n/es_CL.po
odoo/addons/l10n_it_fatturapa_out/i18n/es_CO.po
odoo/addons/l10n_it_fatturapa_out/i18n/es_CR.po
odoo/addons/l10n_it_fatturapa_out/i18n/es_DO.po
odoo/addons/l10n_it_fatturapa_out/i18n/es_EC.po
odoo/addons/l10n_it_fatturapa_out/i18n/es_ES.po
odoo/addons/l10n_it_fatturapa_out/i18n/es_MX.po
odoo/addons/l10n_it_fatturapa_out/i18n/es_PE.po
odoo/addons/l10n_it_fatturapa_out/i18n/es_PY.po
odoo/addons/l10n_it_fatturapa_out/i18n/es_VE.po
odoo/addons/l10n_it_fatturapa_out/i18n/et.po
odoo/addons/l10n_it_fatturapa_out/i18n/eu.po
odoo/addons/l10n_it_fatturapa_out/i18n/fa.po
odoo/addons/l10n_it_fatturapa_out/i18n/fi.po
odoo/addons/l10n_it_fatturapa_out/i18n/fr.po
odoo/addons/l10n_it_fatturapa_out/i18n/fr_CA.po
odoo/addons/l10n_it_fatturapa_out/i18n/fr_CH.po
odoo/addons/l10n_it_fatturapa_out/i18n/fr_FR.po
odoo/addons/l10n_it_fatturapa_out/i18n/gl.po
odoo/addons/l10n_it_fatturapa_out/i18n/gl_ES.po
odoo/addons/l10n_it_fatturapa_out/i18n/he.po
odoo/addons/l10n_it_fatturapa_out/i18n/hi.po
odoo/addons/l10n_it_fatturapa_out/i18n/hr.po
odoo/addons/l10n_it_fatturapa_out/i18n/hr_HR.po
odoo12_addon_l10n_it_fatturapa_out-12.0.3.2.3.dist-info/METADATA
odoo12_addon_l10n_it_fatturapa_out-12.0.3.2.3.dist-info/WHEEL
odoo12_addon_l10n_it_fatturapa_out-12.0.3.2.3.dist-info/top_level.txt
odoo12_addon_l10n_it_fatturapa_out-12.0.3.2.3.dist-info/RECORD
